actfw_raspberrypi/__init__.py
actfw_raspberrypi/capture.py
actfw_raspberrypi/display.py
actfw_raspberrypi/edid.py
actfw_raspberrypi/py.typed
actfw_raspberrypi/vc4/__init__.py
actfw_raspberrypi/vc4/display.py
actfw_raspberrypi/vc4/dispmanx.py
actfw_raspberrypi/vc4/drm/__init__.py
actfw_raspberrypi/vc4/drm/display.py
actfw_raspberrypi/vc4/drm/drm.py
actfw_raspberrypi-3.3.1.dist-info/LICENSE.txt
actfw_raspberrypi-3.3.1.dist-info/METADATA
actfw_raspberrypi-3.3.1.dist-info/WHEEL
actfw_raspberrypi-3.3.1.dist-info/RECORD
