Metadata-Version: 2.3
Name: actfw-raspberrypi
Version: 3.3.1
Summary: actfw's additional components for RaspberryPi
License: MIT
Keywords: actcast
Author: Idein Inc.
Requires-Python: >=3.7,<4.0
Classifier: Development Status :: 4 - Beta
Classifier: Intended Audience :: Developers
Classifier: License :: OSI Approved :: MIT License
Classifier: Programming Language :: Python :: 3
Classifier: Programming Language :: Python :: 3.7
Classifier: Programming Language :: Python :: 3.8
Classifier: Programming Language :: Python :: 3.9
Classifier: Programming Language :: Python :: 3.10
Classifier: Programming Language :: Python :: 3.11
Classifier: Programming Language :: Python :: 3.12
Classifier: Programming Language :: Python :: 3.13
Classifier: Programming Language :: Python :: 3 :: Only
Requires-Dist: actfw-core (>=2.2.0)
Project-URL: Changelog, https://github.com/Idein/actfw-raspberrypi/blob/master/CHANGELOG.md
Project-URL: Documentation, https://idein.github.io/actfw-raspberrypi/latest/
Project-URL: Repository, https://github.com/Idein/actfw-raspberrypi
